MANIFEST.in
README.md
requirements.txt
setup.py
test_requirements.txt
supervisor_logging/__init__.py
supervisor_logging.egg-info/PKG-INFO
supervisor_logging.egg-info/SOURCES.txt
supervisor_logging.egg-info/dependency_links.txt
supervisor_logging.egg-info/entry_points.txt
supervisor_logging.egg-info/top_level.txt