Metadata-Version: 1.0
Name: supervisor-logging
Version: 0.0.9
Summary: Stream supervisord logs to a syslog instance
Home-page: https://github.com/infoxchange/supervisor-logging
Author: Infoxchange development team
Author-email: devs@infoxchange.net.au
License: Apache 2.0
Platform: UNKNOWN
